hashreport/__init__.py
hashreport/cli.py
hashreport/config.py
hashreport/default_config.toml
hashreport/reports/__init__.py
hashreport/reports/base.py
hashreport/reports/compare_handler.py
hashreport/reports/csv_handler.py
hashreport/reports/filelist_handler.py
hashreport/reports/json_handler.py
hashreport/utils/__init__.py
hashreport/utils/conversions.py
hashreport/utils/email_sender.py
hashreport/utils/exceptions.py
hashreport/utils/filters.py
hashreport/utils/hasher.py
hashreport/utils/log_config.py
hashreport/utils/progress_bar.py
hashreport/utils/scanner.py
hashreport/utils/thread_pool.py
hashreport/utils/type_defs.py
hashreport/utils/viewer.py
hashreport/version.py
hashreport-1.1.0.dist-info/LICENSE
hashreport-1.1.0.dist-info/METADATA
hashreport-1.1.0.dist-info/WHEEL
hashreport-1.1.0.dist-info/entry_points.txt
hashreport-1.1.0.dist-info/RECORD
