Metadata-Version: 2.1
Name: hashreport
Version: 1.1.0
Summary: Generate detailed file hash reports quickly and efficiently. Process large numbers of files with multiple filtering options.
License: AGPL-3.0
Keywords: checksum,file,hash,hashing,integrity,report,security,utility,verification
Author: Jake Wells
Author-email: hashreport@fastmail.com
Requires-Python: >=3.10,<3.14
Classifier: Development Status :: 4 - Beta
Classifier: Environment :: Console
Classifier: Intended Audience :: Information Technology
Classifier: License :: OSI Approved :: GNU Affero General Public License v3
Classifier: Natural Language :: English
Classifier: Operating System :: OS Independent
Classifier: Programming Language :: Python
Classifier: Programming Language :: Python :: 3
Classifier: Programming Language :: Python :: 3.10
Classifier: Programming Language :: Python :: 3.11
Classifier: Programming Language :: Python :: 3 :: Only
Classifier: Programming Language :: Python :: 3.12
Classifier: Programming Language :: Python :: 3.13
Classifier: Topic :: Security
Classifier: Topic :: Utilities
Requires-Dist: click (>=8.1.8,<9.0.0)
Requires-Dist: psutil (>=7.0.0,<8.0.0)
Requires-Dist: rich (>=13.9.4,<15.0.0)
Requires-Dist: tomli (>=2.2.1,<3.0.0)
Requires-Dist: tqdm (>=4.67.1,<5.0.0)
Requires-Dist: typing-extensions (>=4.12.2,<5.0.0)
Project-URL: Documentation, https://madebyjake.github.io/hashreport/
Project-URL: Issues, https://github.com/madebyjake/hashreport/issues
Project-URL: Repository, https://github.com/madebyjake/hashreport
